{"status": {"success": true, "httpstatuscode": 200}, "statistics": {"pagetitle": "OAS: Observed Antibody Space", "pageurl": "http://opig.stats.ox.ac.uk/webapps/oas", "time": 2.61, "creditsremaining": 19157, "allitemcount": 22, "totalelements": 93, "waveurl": "http://wave.webaim.org/report?url=http://opig.stats.ox.ac.uk/webapps/oas"}, "categories": {"error": {"description": "Errors", "count": 5, "items": {"alt_missing": {"id": "alt_missing", "description": "Missing alternative text", "count": 1}, "alt_link_missing": {"id": "alt_link_missing", "description": "Linked image missing alternative text", "count": 2}, "language_missing": {"id": "language_missing", "description": "Language missing or invalid", "count": 1}, "button_empty": {"id": "button_empty", "description": "Empty button", "count": 1}}}, "contrast": {"description": "Contrast Errors", "count": 4, "items": {"contrast": {"id": "contrast", "description": "Very low contrast", "count": 4}}}, "alert": {"description": "Alerts", "count": 1, "items": {"h1_missing": {"id": "h1_missing", "description": "Missing first level heading", "count": 1}}}, "feature": {"description": "Features", "count": 0, "items": []}, "structure": {"description": "Structural Elements", "count": 3, "items": {"h4": {"id": "h4", "description": "Heading level 4", "count": 1}, "ul": {"id": "ul", "description": "Unordered list", "count": 1}, "nav": {"id": "nav", "description": "Navigation", "count": 1}}}, "aria": {"description": "ARIA", "count": 9, "items": {"aria_button": {"id": "aria_button", "description": "ARIA button", "count": 3}, "aria_expanded": {"id": "aria_expanded", "description": "ARIA expanded", "count": 3}, "aria_haspopup": {"id": "aria_haspopup", "description": "ARIA popup", "count": 3}}}}}