{"status": {"success": true, "httpstatuscode": 200}, "statistics": {"pagetitle": "Cistrome DB", "pageurl": "http://cistrome.org/db", "time": 1.91, "creditsremaining": 20983, "allitemcount": 123, "totalelements": 436, "waveurl": "http://wave.webaim.org/report?url=http://cistrome.org/db"}, "categories": {"error": {"description": "Errors", "count": 23, "items": {"alt_missing": {"id": "alt_missing", "description": "Missing alternative text", "count": 2}, "label_missing": {"id": "label_missing", "description": "Missing form label", "count": 15}, "language_missing": {"id": "language_missing", "description": "Language missing or invalid", "count": 1}, "button_empty": {"id": "button_empty", "description": "Empty button", "count": 2}, "link_empty": {"id": "link_empty", "description": "Empty link", "count": 1}, "aria_menu_broken": {"id": "aria_menu_broken", "description": "Broken ARIA menu", "count": 2}}}, "contrast": {"description": "Contrast Errors", "count": 14, "items": {"contrast": {"id": "contrast", "description": "Very low contrast", "count": 14}}}, "alert": {"description": "Alerts", "count": 19, "items": {"label_orphaned": {"id": "label_orphaned", "description": "Orphaned form label", "count": 16}, "heading_possible": {"id": "heading_possible", "description": "Possible heading", "count": 1}, "table_caption_possible": {"id": "table_caption_possible", "description": "Possible table caption", "count": 1}, "noscript": {"id": "noscript", "description": "Noscript element", "count": 1}}}, "feature": {"description": "Features", "count": 0, "items": []}, "structure": {"description": "Structural Elements", "count": 52, "items": {"table_data": {"id": "table_data", "description": "Data table", "count": 5}, "th": {"id": "th", "description": "Table header cell", "count": 20}, "h1": {"id": "h1", "description": "Heading level 1", "count": 1}, "h2": {"id": "h2", "description": "Heading level 2", "count": 6}, "ul": {"id": "ul", "description": "Unordered list", "count": 17}, "iframe": {"id": "iframe", "description": "Inline frame", "count": 2}, "nav": {"id": "nav", "description": "Navigation", "count": 1}}}, "aria": {"description": "ARIA", "count": 15, "items": {"aria": {"id": "aria", "description": "ARIA", "count": 10}, "aria_label": {"id": "aria_label", "description": "ARIA label", "count": 1}, "aria_tabindex": {"id": "aria_tabindex", "description": "ARIA tabindex", "count": 2}, "aria_live_region": {"id": "aria_live_region", "description": "ARIA alert or live region", "count": 1}, "aria_menu": {"id": "aria_menu", "description": "ARIA menu", "count": 1}}}}}