{"status": {"success": true, "httpstatuscode": 200}, "statistics": {"pagetitle": "Home \u00b7 NucMap", "pageurl": "http://bigd.big.ac.cn/nucmap", "time": 8.32, "creditsremaining": 18459, "allitemcount": 95, "totalelements": 330, "waveurl": "http://wave.webaim.org/report?url=http://bigd.big.ac.cn/nucmap"}, "categories": {"error": {"description": "Errors", "count": 3, "items": {"alt_missing": {"id": "alt_missing", "description": "Missing alternative text", "count": 1}, "alt_link_missing": {"id": "alt_link_missing", "description": "Linked image missing alternative text", "count": 2}}}, "contrast": {"description": "Contrast Errors", "count": 34, "items": {"contrast": {"id": "contrast", "description": "Very low contrast", "count": 34}}}, "alert": {"description": "Alerts", "count": 9, "items": {"h1_missing": {"id": "h1_missing", "description": "Missing first level heading", "count": 1}, "heading_possible": {"id": "heading_possible", "description": "Possible heading", "count": 6}, "link_redundant": {"id": "link_redundant", "description": "Redundant link", "count": 1}, "noscript": {"id": "noscript", "description": "Noscript element", "count": 1}}}, "feature": {"description": "Features", "count": 8, "items": {"alt": {"id": "alt", "description": "Alternative text", "count": 1}, "alt_link": {"id": "alt_link", "description": "Linked image with alternative text", "count": 6}, "lang": {"id": "lang", "description": "Language", "count": 1}}}, "structure": {"description": "Structural Elements", "count": 28, "items": {"h3": {"id": "h3", "description": "Heading level 3", "count": 6}, "h5": {"id": "h5", "description": "Heading level 5", "count": 4}, "ul": {"id": "ul", "description": "Unordered list", "count": 13}, "header": {"id": "header", "description": "Header", "count": 1}, "nav": {"id": "nav", "description": "Navigation", "count": 2}, "main": {"id": "main", "description": "Main content", "count": 1}, "footer": {"id": "footer", "description": "Footer", "count": 1}}}, "aria": {"description": "ARIA", "count": 13, "items": {"aria": {"id": "aria", "description": "ARIA", "count": 2}, "aria_label": {"id": "aria_label", "description": "ARIA label", "count": 6}, "aria_live_region": {"id": "aria_live_region", "description": "ARIA alert or live region", "count": 1}, "aria_expanded": {"id": "aria_expanded", "description": "ARIA expanded", "count": 4}}}}}