{"status": {"success": true, "httpstatuscode": 200}, "statistics": {"pagetitle": "The SPRED1 gene homepage - Global Variome shared LOVD", "pageurl": "http://www.lovd.nl/SPRED1", "time": 4.21, "creditsremaining": 18327, "allitemcount": 163, "totalelements": 595, "waveurl": "http://wave.webaim.org/report?url=http://www.lovd.nl/SPRED1"}, "categories": {"error": {"description": "Errors", "count": 5, "items": {"language_missing": {"id": "language_missing", "description": "Language missing or invalid", "count": 1}, "heading_empty": {"id": "heading_empty", "description": "Empty heading", "count": 1}, "th_empty": {"id": "th_empty", "description": "Empty table header", "count": 3}}}, "contrast": {"description": "Contrast Errors", "count": 0, "items": []}, "alert": {"description": "Alerts", "count": 25, "items": {"image_title": {"id": "image_title", "description": "Image with title", "count": 1}, "label_title": {"id": "label_title", "description": "Unlabeled form control with title", "count": 6}, "region_missing": {"id": "region_missing", "description": "No page regions", "count": 1}, "h1_missing": {"id": "h1_missing", "description": "Missing first level heading", "count": 1}, "heading_skipped": {"id": "heading_skipped", "description": "Skipped heading level", "count": 2}, "event_handler": {"id": "event_handler", "description": "Device dependent event handler", "count": 7}, "title_redundant": {"id": "title_redundant", "description": "Redundant title text", "count": 2}, "table_layout": {"id": "table_layout", "description": "Layout table", "count": 5}}}, "feature": {"description": "Features", "count": 35, "items": {"alt": {"id": "alt", "description": "Alternative text", "count": 4}, "alt_null": {"id": "alt_null", "description": "Null or empty alternative text", "count": 16}, "alt_spacer": {"id": "alt_spacer", "description": "Null or empty alternative text on spacer", "count": 6}, "alt_link": {"id": "alt_link", "description": "Linked image with alternative text", "count": 9}}}, "structure": {"description": "Structural Elements", "count": 98, "items": {"table_data": {"id": "table_data", "description": "Data table", "count": 7}, "th": {"id": "th", "description": "Table header cell", "count": 77}, "h2": {"id": "h2", "description": "Heading level 2", "count": 4}, "h4": {"id": "h4", "description": "Heading level 4", "count": 1}, "h5": {"id": "h5", "description": "Heading level 5", "count": 2}, "ul": {"id": "ul", "description": "Unordered list", "count": 7}}}, "aria": {"description": "ARIA", "count": 0, "items": []}}}