{"status": {"success": true, "httpstatuscode": 200}, "statistics": {"pagetitle": "P-SAMS: the Plant Small RNA Maker Suite", "pageurl": "http://p-sams.carringtonlab.org/", "time": 2.01, "creditsremaining": 18093, "allitemcount": 14, "totalelements": 69, "waveurl": "http://wave.webaim.org/report?url=http://p-sams.carringtonlab.org/"}, "categories": {"error": {"description": "Errors", "count": 3, "items": {"alt_missing": {"id": "alt_missing", "description": "Missing alternative text", "count": 2}, "button_empty": {"id": "button_empty", "description": "Empty button", "count": 1}}}, "contrast": {"description": "Contrast Errors", "count": 7, "items": {"contrast": {"id": "contrast", "description": "Very low contrast", "count": 7}}}, "alert": {"description": "Alerts", "count": 0, "items": []}, "feature": {"description": "Features", "count": 1, "items": {"lang": {"id": "lang", "description": "Language", "count": 1}}}, "structure": {"description": "Structural Elements", "count": 3, "items": {"h1": {"id": "h1", "description": "Heading level 1", "count": 1}, "ul": {"id": "ul", "description": "Unordered list", "count": 1}, "footer": {"id": "footer", "description": "Footer", "count": 1}}}, "aria": {"description": "ARIA", "count": 0, "items": []}}}