{"status": {"success": true, "httpstatuscode": 200}, "statistics": {"pagetitle": "iUUCD 2.0 - integrated annotations for ubiquitin and ubiquitin-like conjugation database", "pageurl": "http://iuucd.biocuckoo.org", "time": 5.11, "creditsremaining": 18027, "allitemcount": 179, "totalelements": 682, "waveurl": "http://wave.webaim.org/report?url=http://iuucd.biocuckoo.org"}, "categories": {"error": {"description": "Errors", "count": 19, "items": {"alt_missing": {"id": "alt_missing", "description": "Missing alternative text", "count": 14}, "alt_link_missing": {"id": "alt_link_missing", "description": "Linked image missing alternative text", "count": 2}, "label_missing": {"id": "label_missing", "description": "Missing form label", "count": 1}, "language_missing": {"id": "language_missing", "description": "Language missing or invalid", "count": 1}, "heading_empty": {"id": "heading_empty", "description": "Empty heading", "count": 1}}}, "contrast": {"description": "Contrast Errors", "count": 107, "items": {"contrast": {"id": "contrast", "description": "Very low contrast", "count": 107}}}, "alert": {"description": "Alerts", "count": 47, "items": {"select_missing_label": {"id": "select_missing_label", "description": "Select missing label", "count": 1}, "region_missing": {"id": "region_missing", "description": "No page regions", "count": 1}, "h1_missing": {"id": "h1_missing", "description": "Missing first level heading", "count": 1}, "link_suspicious": {"id": "link_suspicious", "description": "Suspicious link text", "count": 1}, "link_pdf": {"id": "link_pdf", "description": "Link to PDF document", "count": 2}, "event_handler": {"id": "event_handler", "description": "Device dependent event handler", "count": 37}, "text_justified": {"id": "text_justified", "description": "Justified text", "count": 3}, "table_layout": {"id": "table_layout", "description": "Layout table", "count": 1}}}, "feature": {"description": "Features", "count": 0, "items": []}, "structure": {"description": "Structural Elements", "count": 6, "items": {"h3": {"id": "h3", "description": "Heading level 3", "count": 1}, "ul": {"id": "ul", "description": "Unordered list", "count": 5}}}, "aria": {"description": "ARIA", "count": 0, "items": []}}}