{"status": {"success": true, "httpstatuscode": 200}, "statistics": {"pagetitle": "EnteroBase", "pageurl": "http://enterobase.warwick.ac.uk", "time": 3.92, "creditsremaining": 17777, "allitemcount": 44, "totalelements": 286, "waveurl": "http://wave.webaim.org/report?url=http://enterobase.warwick.ac.uk"}, "categories": {"error": {"description": "Errors", "count": 3, "items": {"alt_link_missing": {"id": "alt_link_missing", "description": "Linked image missing alternative text", "count": 2}, "language_missing": {"id": "language_missing", "description": "Language missing or invalid", "count": 1}}}, "contrast": {"description": "Contrast Errors", "count": 14, "items": {"contrast": {"id": "contrast", "description": "Very low contrast", "count": 14}}}, "alert": {"description": "Alerts", "count": 11, "items": {"h1_missing": {"id": "h1_missing", "description": "Missing first level heading", "count": 1}, "link_suspicious": {"id": "link_suspicious", "description": "Suspicious link text", "count": 1}, "event_handler": {"id": "event_handler", "description": "Device dependent event handler", "count": 9}}}, "feature": {"description": "Features", "count": 0, "items": []}, "structure": {"description": "Structural Elements", "count": 16, "items": {"h4": {"id": "h4", "description": "Heading level 4", "count": 3}, "ul": {"id": "ul", "description": "Unordered list", "count": 11}, "nav": {"id": "nav", "description": "Navigation", "count": 1}, "footer": {"id": "footer", "description": "Footer", "count": 1}}}, "aria": {"description": "ARIA", "count": 0, "items": []}}}