{"status": {"success": true, "httpstatuscode": 200}, "statistics": {"pagetitle": "gtrd", "pageurl": "http://gtrd.biouml.org/", "time": 7.12, "creditsremaining": 20723, "allitemcount": 387, "totalelements": 1331, "waveurl": "http://wave.webaim.org/report?url=http://gtrd.biouml.org/"}, "categories": {"error": {"description": "Errors", "count": 31, "items": {"alt_missing": {"id": "alt_missing", "description": "Missing alternative text", "count": 31}}}, "contrast": {"description": "Contrast Errors", "count": 170, "items": {"contrast": {"id": "contrast", "description": "Very low contrast", "count": 170}}}, "alert": {"description": "Alerts", "count": 18, "items": {"h1_missing": {"id": "h1_missing", "description": "Missing first level heading", "count": 1}, "heading_skipped": {"id": "heading_skipped", "description": "Skipped heading level", "count": 1}, "link_internal_broken": {"id": "link_internal_broken", "description": "Broken same-page link", "count": 16}}}, "feature": {"description": "Features", "count": 1, "items": {"lang": {"id": "lang", "description": "Language", "count": 1}}}, "structure": {"description": "Structural Elements", "count": 87, "items": {"table_data": {"id": "table_data", "description": "Data table", "count": 10}, "th": {"id": "th", "description": "Table header cell", "count": 38}, "h2": {"id": "h2", "description": "Heading level 2", "count": 9}, "h3": {"id": "h3", "description": "Heading level 3", "count": 10}, "h4": {"id": "h4", "description": "Heading level 4", "count": 7}, "ol": {"id": "ol", "description": "Ordered list", "count": 9}, "ul": {"id": "ul", "description": "Unordered list", "count": 3}, "nav": {"id": "nav", "description": "Navigation", "count": 1}}}, "aria": {"description": "ARIA", "count": 80, "items": {"aria": {"id": "aria", "description": "ARIA", "count": 24}, "aria_label": {"id": "aria_label", "description": "ARIA label", "count": 8}, "aria_tabindex": {"id": "aria_tabindex", "description": "ARIA tabindex", "count": 13}, "aria_menu": {"id": "aria_menu", "description": "ARIA menu", "count": 3}, "aria_button": {"id": "aria_button", "description": "ARIA button", "count": 16}, "aria_hidden": {"id": "aria_hidden", "description": "ARIA hidden", "count": 3}, "aria_expanded": {"id": "aria_expanded", "description": "ARIA expanded", "count": 10}, "aria_haspopup": {"id": "aria_haspopup", "description": "ARIA popup", "count": 3}}}}}