{"status": {"success": true, "httpstatuscode": 200}, "statistics": {"pagetitle": "ASRA", "pageurl": "https://www.ccb.uni-saarland.de/asra", "time": 5.72, "creditsremaining": 16005, "allitemcount": 93, "totalelements": 320, "waveurl": "http://wave.webaim.org/report?url=https://www.ccb.uni-saarland.de/asra"}, "categories": {"error": {"description": "Errors", "count": 3, "items": {"label_missing": {"id": "label_missing", "description": "Missing form label", "count": 1}, "aria_reference_broken": {"id": "aria_reference_broken", "description": "Broken ARIA reference", "count": 2}}}, "contrast": {"description": "Contrast Errors", "count": 2, "items": {"contrast": {"id": "contrast", "description": "Very low contrast", "count": 2}}}, "alert": {"description": "Alerts", "count": 3, "items": {"h1_missing": {"id": "h1_missing", "description": "Missing first level heading", "count": 1}, "noscript": {"id": "noscript", "description": "Noscript element", "count": 2}}}, "feature": {"description": "Features", "count": 5, "items": {"alt": {"id": "alt", "description": "Alternative text", "count": 1}, "alt_link": {"id": "alt_link", "description": "Linked image with alternative text", "count": 3}, "lang": {"id": "lang", "description": "Language", "count": 1}}}, "structure": {"description": "Structural Elements", "count": 9, "items": {"h5": {"id": "h5", "description": "Heading level 5", "count": 1}, "h6": {"id": "h6", "description": "Heading level 6", "count": 1}, "ul": {"id": "ul", "description": "Unordered list", "count": 4}, "header": {"id": "header", "description": "Header", "count": 1}, "nav": {"id": "nav", "description": "Navigation", "count": 1}, "main": {"id": "main", "description": "Main content", "count": 1}}}, "aria": {"description": "ARIA", "count": 71, "items": {"aria": {"id": "aria", "description": "ARIA", "count": 20}, "aria_label": {"id": "aria_label", "description": "ARIA label", "count": 5}, "aria_tabindex": {"id": "aria_tabindex", "description": "ARIA tabindex", "count": 14}, "aria_button": {"id": "aria_button", "description": "ARIA button", "count": 14}, "aria_hidden": {"id": "aria_hidden", "description": "ARIA hidden", "count": 16}, "aria_expanded": {"id": "aria_expanded", "description": "ARIA expanded", "count": 1}, "aria_haspopup": {"id": "aria_haspopup", "description": "ARIA popup", "count": 1}}}}}