{"status": {"success": true, "httpstatuscode": 200}, "statistics": {"pagetitle": "PRRDB: Pattern-recognition receptor database", "pageurl": "http://crdd.osdd.net/raghava/prrdb", "time": 3.51, "creditsremaining": 15485, "allitemcount": 15, "totalelements": 63, "waveurl": "http://wave.webaim.org/report?url=http://crdd.osdd.net/raghava/prrdb"}, "categories": {"error": {"description": "Errors", "count": 5, "items": {"alt_missing": {"id": "alt_missing", "description": "Missing alternative text", "count": 1}, "alt_area_missing": {"id": "alt_area_missing", "description": "Image map area missing alternative text", "count": 1}, "alt_map_missing": {"id": "alt_map_missing", "description": "Image map missing alternative text", "count": 2}, "language_missing": {"id": "language_missing", "description": "Language missing or invalid", "count": 1}}}, "contrast": {"description": "Contrast Errors", "count": 1, "items": {"contrast": {"id": "contrast", "description": "Very low contrast", "count": 1}}}, "alert": {"description": "Alerts", "count": 8, "items": {"heading_missing": {"id": "heading_missing", "description": "No heading structure", "count": 1}, "region_missing": {"id": "region_missing", "description": "No page regions", "count": 1}, "text_justified": {"id": "text_justified", "description": "Justified text", "count": 1}, "table_layout": {"id": "table_layout", "description": "Layout table", "count": 5}}}, "feature": {"description": "Features", "count": 1, "items": {"alt_link": {"id": "alt_link", "description": "Linked image with alternative text", "count": 1}}}, "structure": {"description": "Structural Elements", "count": 0, "items": []}, "aria": {"description": "ARIA", "count": 0, "items": []}}}