{"status": {"success": true, "httpstatuscode": 200}, "statistics": {"pagetitle": "Chemie - Philipps-Universit\u00e4t Marburg", "pageurl": "http://www.chemie.uni-marburg.de/~csdbase/", "time": 4.51, "creditsremaining": 14791, "allitemcount": 364, "totalelements": 1255, "waveurl": "http://wave.webaim.org/report?url=http://www.chemie.uni-marburg.de/~csdbase/"}, "categories": {"error": {"description": "Errors", "count": 5, "items": {"alt_missing": {"id": "alt_missing", "description": "Missing alternative text", "count": 4}, "link_empty": {"id": "link_empty", "description": "Empty link", "count": 1}}}, "contrast": {"description": "Contrast Errors", "count": 34, "items": {"contrast": {"id": "contrast", "description": "Very low contrast", "count": 34}}}, "alert": {"description": "Alerts", "count": 23, "items": {"label_orphaned": {"id": "label_orphaned", "description": "Orphaned form label", "count": 1}, "link_redundant": {"id": "link_redundant", "description": "Redundant link", "count": 21}, "noscript": {"id": "noscript", "description": "Noscript element", "count": 1}}}, "feature": {"description": "Features", "count": 27, "items": {"alt": {"id": "alt", "description": "Alternative text", "count": 1}, "alt_null": {"id": "alt_null", "description": "Null or empty alternative text", "count": 22}, "figure": {"id": "figure", "description": "Figure", "count": 1}, "label": {"id": "label", "description": "Form label", "count": 2}, "lang": {"id": "lang", "description": "Language", "count": 1}}}, "structure": {"description": "Structural Elements", "count": 107, "items": {"h1": {"id": "h1", "description": "Heading level 1", "count": 3}, "h2": {"id": "h2", "description": "Heading level 2", "count": 13}, "h3": {"id": "h3", "description": "Heading level 3", "count": 15}, "h4": {"id": "h4", "description": "Heading level 4", "count": 12}, "h6": {"id": "h6", "description": "Heading level 6", "count": 6}, "ul": {"id": "ul", "description": "Unordered list", "count": 45}, "header": {"id": "header", "description": "Header", "count": 1}, "nav": {"id": "nav", "description": "Navigation", "count": 10}, "main": {"id": "main", "description": "Main content", "count": 1}, "footer": {"id": "footer", "description": "Footer", "count": 1}}}, "aria": {"description": "ARIA", "count": 168, "items": {"aria": {"id": "aria", "description": "ARIA", "count": 124}, "aria_label": {"id": "aria_label", "description": "ARIA label", "count": 3}, "aria_tabindex": {"id": "aria_tabindex", "description": "ARIA tabindex", "count": 17}, "aria_menu": {"id": "aria_menu", "description": "ARIA menu", "count": 1}, "aria_button": {"id": "aria_button", "description": "ARIA button", "count": 1}, "aria_hidden": {"id": "aria_hidden", "description": "ARIA hidden", "count": 8}, "aria_expanded": {"id": "aria_expanded", "description": "ARIA expanded", "count": 14}}}}}