{"status": {"success": true, "httpstatuscode": 200}, "statistics": {"pagetitle": "Dr.Nagendra Kumar Singh", "pageurl": "http://nksingh.nationalprof.in", "time": 6.83, "creditsremaining": 14683, "allitemcount": 98, "totalelements": 431, "waveurl": "http://wave.webaim.org/report?url=http://nksingh.nationalprof.in"}, "categories": {"error": {"description": "Errors", "count": 17, "items": {"alt_missing": {"id": "alt_missing", "description": "Missing alternative text", "count": 6}, "alt_link_missing": {"id": "alt_link_missing", "description": "Linked image missing alternative text", "count": 6}, "language_missing": {"id": "language_missing", "description": "Language missing or invalid", "count": 1}, "heading_empty": {"id": "heading_empty", "description": "Empty heading", "count": 1}, "link_empty": {"id": "link_empty", "description": "Empty link", "count": 3}}}, "contrast": {"description": "Contrast Errors", "count": 13, "items": {"contrast": {"id": "contrast", "description": "Very low contrast", "count": 13}}}, "alert": {"description": "Alerts", "count": 24, "items": {"alt_long": {"id": "alt_long", "description": "Long alternative text", "count": 2}, "h1_missing": {"id": "h1_missing", "description": "Missing first level heading", "count": 1}, "heading_skipped": {"id": "heading_skipped", "description": "Skipped heading level", "count": 2}, "link_internal_broken": {"id": "link_internal_broken", "description": "Broken same-page link", "count": 5}, "link_suspicious": {"id": "link_suspicious", "description": "Suspicious link text", "count": 1}, "link_redundant": {"id": "link_redundant", "description": "Redundant link", "count": 6}, "text_justified": {"id": "text_justified", "description": "Justified text", "count": 5}, "html5_video_audio": {"id": "html5_video_audio", "description": "HTML5 video or audio", "count": 2}}}, "feature": {"description": "Features", "count": 9, "items": {"alt": {"id": "alt", "description": "Alternative text", "count": 1}, "alt_null": {"id": "alt_null", "description": "Null or empty alternative text", "count": 2}, "figure": {"id": "figure", "description": "Figure", "count": 6}}}, "structure": {"description": "Structural Elements", "count": 34, "items": {"h3": {"id": "h3", "description": "Heading level 3", "count": 7}, "h4": {"id": "h4", "description": "Heading level 4", "count": 4}, "h5": {"id": "h5", "description": "Heading level 5", "count": 7}, "ul": {"id": "ul", "description": "Unordered list", "count": 11}, "iframe": {"id": "iframe", "description": "Inline frame", "count": 3}, "header": {"id": "header", "description": "Header", "count": 1}, "nav": {"id": "nav", "description": "Navigation", "count": 1}}}, "aria": {"description": "ARIA", "count": 1, "items": {"aria_button": {"id": "aria_button", "description": "ARIA button", "count": 1}}}}}