{"status": {"success": true, "httpstatuscode": 200}, "statistics": {"pagetitle": "RiceNCexp: Rice Non-coding RNA Expression Altas", "pageurl": "https://cbi.njau.edu.cn/RiceNCexp/", "time": 7.63, "creditsremaining": 13981, "allitemcount": 24, "totalelements": 109, "waveurl": "http://wave.webaim.org/report?url=https://cbi.njau.edu.cn/RiceNCexp/"}, "categories": {"error": {"description": "Errors", "count": 1, "items": {"language_missing": {"id": "language_missing", "description": "Language missing or invalid", "count": 1}}}, "contrast": {"description": "Contrast Errors", "count": 9, "items": {"contrast": {"id": "contrast", "description": "Very low contrast", "count": 9}}}, "alert": {"description": "Alerts", "count": 5, "items": {"h1_missing": {"id": "h1_missing", "description": "Missing first level heading", "count": 1}, "link_redundant": {"id": "link_redundant", "description": "Redundant link", "count": 2}, "text_justified": {"id": "text_justified", "description": "Justified text", "count": 2}}}, "feature": {"description": "Features", "count": 2, "items": {"alt_null": {"id": "alt_null", "description": "Null or empty alternative text", "count": 1}, "alt_link": {"id": "alt_link", "description": "Linked image with alternative text", "count": 1}}}, "structure": {"description": "Structural Elements", "count": 3, "items": {"h3": {"id": "h3", "description": "Heading level 3", "count": 1}, "nav": {"id": "nav", "description": "Navigation", "count": 1}, "footer": {"id": "footer", "description": "Footer", "count": 1}}}, "aria": {"description": "ARIA", "count": 4, "items": {"aria_hidden": {"id": "aria_hidden", "description": "ARIA hidden", "count": 4}}}}}