{"status": {"success": true, "httpstatuscode": 200}, "statistics": {"pagetitle": "Dory Visualization | DORY", "pageurl": "https://doryworkspace.org/doryviz", "time": 18.64, "creditsremaining": 13511, "allitemcount": 241, "totalelements": 1210, "waveurl": "http://wave.webaim.org/report?url=https://doryworkspace.org/doryviz"}, "categories": {"error": {"description": "Errors", "count": 192, "items": {"alt_missing": {"id": "alt_missing", "description": "Missing alternative text", "count": 191}, "link_skip_broken": {"id": "link_skip_broken", "description": "Broken skip link", "count": 1}}}, "contrast": {"description": "Contrast Errors", "count": 2, "items": {"contrast": {"id": "contrast", "description": "Very low contrast", "count": 2}}}, "alert": {"description": "Alerts", "count": 16, "items": {"link_redundant": {"id": "link_redundant", "description": "Redundant link", "count": 1}, "link_excel": {"id": "link_excel", "description": "Link to Excel spreadsheet", "count": 1}, "javascript_jumpmenu": {"id": "javascript_jumpmenu", "description": "JavaScript jump menu", "count": 6}, "underline": {"id": "underline", "description": "Underlined text", "count": 3}, "title_redundant": {"id": "title_redundant", "description": "Redundant title text", "count": 1}, "table_layout": {"id": "table_layout", "description": "Layout table", "count": 4}}}, "feature": {"description": "Features", "count": 15, "items": {"alt": {"id": "alt", "description": "Alternative text", "count": 5}, "label": {"id": "label", "description": "Form label", "count": 9}, "lang": {"id": "lang", "description": "Language", "count": 1}}}, "structure": {"description": "Structural Elements", "count": 14, "items": {"table_data": {"id": "table_data", "description": "Data table", "count": 1}, "th": {"id": "th", "description": "Table header cell", "count": 1}, "h1": {"id": "h1", "description": "Heading level 1", "count": 1}, "h2": {"id": "h2", "description": "Heading level 2", "count": 4}, "ul": {"id": "ul", "description": "Unordered list", "count": 2}, "header": {"id": "header", "description": "Header", "count": 1}, "nav": {"id": "nav", "description": "Navigation", "count": 2}, "main": {"id": "main", "description": "Main content", "count": 1}, "footer": {"id": "footer", "description": "Footer", "count": 1}}}, "aria": {"description": "ARIA", "count": 2, "items": {"aria_label": {"id": "aria_label", "description": "ARIA label", "count": 2}}}}}