{"status": {"success": true, "httpstatuscode": 200}, "statistics": {"pagetitle": "LIRcentral - Home", "pageurl": "https://lircentral.eu", "time": 2.71, "creditsremaining": 13347, "allitemcount": 30, "totalelements": 421, "waveurl": "http://wave.webaim.org/report?url=https://lircentral.eu"}, "categories": {"error": {"description": "Errors", "count": 2, "items": {"alt_missing": {"id": "alt_missing", "description": "Missing alternative text", "count": 1}, "language_missing": {"id": "language_missing", "description": "Language missing or invalid", "count": 1}}}, "contrast": {"description": "Contrast Errors", "count": 5, "items": {"contrast": {"id": "contrast", "description": "Very low contrast", "count": 5}}}, "alert": {"description": "Alerts", "count": 4, "items": {"h1_missing": {"id": "h1_missing", "description": "Missing first level heading", "count": 1}, "link_redundant": {"id": "link_redundant", "description": "Redundant link", "count": 2}, "text_small": {"id": "text_small", "description": "Very small text", "count": 1}}}, "feature": {"description": "Features", "count": 1, "items": {"alt_link": {"id": "alt_link", "description": "Linked image with alternative text", "count": 1}}}, "structure": {"description": "Structural Elements", "count": 10, "items": {"table_data": {"id": "table_data", "description": "Data table", "count": 2}, "th": {"id": "th", "description": "Table header cell", "count": 4}, "h3": {"id": "h3", "description": "Heading level 3", "count": 1}, "ol": {"id": "ol", "description": "Ordered list", "count": 1}, "ul": {"id": "ul", "description": "Unordered list", "count": 1}, "nav": {"id": "nav", "description": "Navigation", "count": 1}}}, "aria": {"description": "ARIA", "count": 8, "items": {"aria_label": {"id": "aria_label", "description": "ARIA label", "count": 6}, "aria_hidden": {"id": "aria_hidden", "description": "ARIA hidden", "count": 2}}}}}