{"status": {"success": true, "httpstatuscode": 200}, "statistics": {"pagetitle": "Macrophage", "pageurl": "http://macrophage.mouseprotein.cn", "time": 5.02, "creditsremaining": 13177, "allitemcount": 24, "totalelements": 67, "waveurl": "http://wave.webaim.org/report?url=http://macrophage.mouseprotein.cn"}, "categories": {"error": {"description": "Errors", "count": 0, "items": []}, "contrast": {"description": "Contrast Errors", "count": 6, "items": {"contrast": {"id": "contrast", "description": "Very low contrast", "count": 6}}}, "alert": {"description": "Alerts", "count": 9, "items": {"alt_suspicious": {"id": "alt_suspicious", "description": "Suspicious alternative text", "count": 5}, "alt_duplicate": {"id": "alt_duplicate", "description": "A nearby image has the same alternative text", "count": 3}, "noscript": {"id": "noscript", "description": "Noscript element", "count": 1}}}, "feature": {"description": "Features", "count": 1, "items": {"lang": {"id": "lang", "description": "Language", "count": 1}}}, "structure": {"description": "Structural Elements", "count": 5, "items": {"h1": {"id": "h1", "description": "Heading level 1", "count": 1}, "ul": {"id": "ul", "description": "Unordered list", "count": 2}, "nav": {"id": "nav", "description": "Navigation", "count": 1}, "footer": {"id": "footer", "description": "Footer", "count": 1}}}, "aria": {"description": "ARIA", "count": 3, "items": {"aria": {"id": "aria", "description": "ARIA", "count": 1}, "aria_label": {"id": "aria_label", "description": "ARIA label", "count": 1}, "aria_expanded": {"id": "aria_expanded", "description": "ARIA expanded", "count": 1}}}}}