{"status": {"success": true, "httpstatuscode": 200}, "statistics": {"pagetitle": "Neural Stem Cell Institute :: Cortecon", "pageurl": "http://cortecon.neuralsci.org", "time": 5.21, "creditsremaining": 19941, "allitemcount": 56, "totalelements": 628, "waveurl": "http://wave.webaim.org/report?url=http://cortecon.neuralsci.org"}, "categories": {"error": {"description": "Errors", "count": 9, "items": {"alt_missing": {"id": "alt_missing", "description": "Missing alternative text", "count": 1}, "alt_link_missing": {"id": "alt_link_missing", "description": "Linked image missing alternative text", "count": 2}, "label_missing": {"id": "label_missing", "description": "Missing form label", "count": 6}}}, "contrast": {"description": "Contrast Errors", "count": 27, "items": {"contrast": {"id": "contrast", "description": "Very low contrast", "count": 27}}}, "alert": {"description": "Alerts", "count": 7, "items": {"link_suspicious": {"id": "link_suspicious", "description": "Suspicious link text", "count": 1}, "link_redundant": {"id": "link_redundant", "description": "Redundant link", "count": 1}, "event_handler": {"id": "event_handler", "description": "Device dependent event handler", "count": 5}}}, "feature": {"description": "Features", "count": 1, "items": {"lang": {"id": "lang", "description": "Language", "count": 1}}}, "structure": {"description": "Structural Elements", "count": 12, "items": {"h1": {"id": "h1", "description": "Heading level 1", "count": 1}, "h2": {"id": "h2", "description": "Heading level 2", "count": 4}, "ul": {"id": "ul", "description": "Unordered list", "count": 3}, "header": {"id": "header", "description": "Header", "count": 1}, "nav": {"id": "nav", "description": "Navigation", "count": 2}, "footer": {"id": "footer", "description": "Footer", "count": 1}}}, "aria": {"description": "ARIA", "count": 0, "items": []}}}