{"status": {"success": true, "httpstatuscode": 200}, "statistics": {"pagetitle": "InfezMed - Infezmed", "pageurl": "https://www.infezmed.it/", "time": 3.61, "creditsremaining": 5885, "allitemcount": 53, "totalelements": 397, "waveurl": "http://wave.webaim.org/report?url=https://www.infezmed.it/"}, "categories": {"error": {"description": "Errors", "count": 3, "items": {"alt_link_missing": {"id": "alt_link_missing", "description": "Linked image missing alternative text", "count": 1}, "button_empty": {"id": "button_empty", "description": "Empty button", "count": 1}, "link_empty": {"id": "link_empty", "description": "Empty link", "count": 1}}}, "contrast": {"description": "Contrast Errors", "count": 12, "items": {"contrast": {"id": "contrast", "description": "Very low contrast", "count": 12}}}, "alert": {"description": "Alerts", "count": 11, "items": {"alt_long": {"id": "alt_long", "description": "Long alternative text", "count": 1}, "h1_missing": {"id": "h1_missing", "description": "Missing first level heading", "count": 1}, "link_suspicious": {"id": "link_suspicious", "description": "Suspicious link text", "count": 2}, "text_small": {"id": "text_small", "description": "Very small text", "count": 4}, "text_justified": {"id": "text_justified", "description": "Justified text", "count": 2}, "table_layout": {"id": "table_layout", "description": "Layout table", "count": 1}}}, "feature": {"description": "Features", "count": 3, "items": {"alt": {"id": "alt", "description": "Alternative text", "count": 1}, "alt_link": {"id": "alt_link", "description": "Linked image with alternative text", "count": 1}, "lang": {"id": "lang", "description": "Language", "count": 1}}}, "structure": {"description": "Structural Elements", "count": 24, "items": {"h3": {"id": "h3", "description": "Heading level 3", "count": 6}, "ul": {"id": "ul", "description": "Unordered list", "count": 14}, "header": {"id": "header", "description": "Header", "count": 1}, "nav": {"id": "nav", "description": "Navigation", "count": 2}, "footer": {"id": "footer", "description": "Footer", "count": 1}}}, "aria": {"description": "ARIA", "count": 0, "items": []}}}